{"dependencies":[{"name":"/Users/zache/Code/zxdom/package.json","includedInParent":true,"mtime":1525632566093},{"name":"/Users/zache/Code/zxdom/example/.babelrc","includedInParent":true,"mtime":1525465325290}],"generated":{"js":"'use strict';\n\nObject.defineProperty(exports, \"__esModule\", {\n    value: true\n});\nexports.default = h;\n\nfunction _toConsumableArray(arr) { if (Array.isArray(arr)) { for (var i = 0, arr2 = Array(arr.length); i < arr.length; i++) { arr2[i] = arr[i]; } return arr2; } else { return Array.from(arr); } }\n\nfunction h(type, attr) {\n    for (var _len = arguments.length, chld = Array(_len > 2 ? _len - 2 : 0), _key = 2; _key < _len; _key++) {\n        chld[_key - 2] = arguments[_key];\n    }\n\n    var _ref, _ref2;\n\n    attr = attr || {};\n    chld = (_ref = []).concat.apply(_ref, _toConsumableArray((_ref2 = []).concat.apply(_ref2, _toConsumableArray(chld)))); //flatten children into a single array\n    if (!!type.func) return {\n        component: type,\n        vnode: type.func(Object.assign({}, attr, type.state), chld),\n        attr: attr,\n        chld: chld\n    };\n    if (typeof type === 'function') return type(attr, chld);\n    return { tag: type, attr: attr, chld: chld };\n}","map":{"mappings":[{"name":"h","generated":{"line":6,"column":18},"source":"../src/h.js","original":{"line":2,"column":24}},{"generated":{"line":10,"column":0},"source":"../src/h.js","original":{"line":2,"column":15}},{"name":"h","generated":{"line":10,"column":9},"source":"../src/h.js","original":{"line":2,"column":24}},{"generated":{"line":10,"column":10},"source":"../src/h.js","original":{"line":2,"column":15}},{"name":"type","generated":{"line":10,"column":11},"source":"../src/h.js","original":{"line":2,"column":26}},{"generated":{"line":10,"column":15},"source":"../src/h.js","original":{"line":2,"column":15}},{"name":"attr","generated":{"line":10,"column":17},"source":"../src/h.js","original":{"line":2,"column":32}},{"generated":{"line":10,"column":21},"source":"../src/h.js","original":{"line":2,"column":15}},{"generated":{"line":10,"column":23},"source":"../src/h.js","original":{"line":2,"column":47}},{"generated":{"line":11,"column":0},"source":"../src/h.js","original":{"line":2,"column":47}},{"name":"chld","generated":{"line":11,"column":38},"source":"../src/h.js","original":{"line":2,"column":41}},{"generated":{"line":11,"column":42},"source":"../src/h.js","original":{"line":2,"column":47}},{"name":"chld","generated":{"line":12,"column":0},"source":"../src/h.js","original":{"line":2,"column":41}},{"generated":{"line":12,"column":12},"source":"../src/h.js","original":{"line":2,"column":47}},{"generated":{"line":13,"column":0},"source":"../src/h.js","original":{"line":2,"column":47}},{"generated":{"line":15,"column":0},"source":"../src/h.js","original":{"line":2,"column":47}},{"name":"attr","generated":{"line":17,"column":0},"source":"../src/h.js","original":{"line":3,"column":4}},{"name":"attr","generated":{"line":17,"column":11},"source":"../src/h.js","original":{"line":3,"column":11}},{"generated":{"line":17,"column":19},"source":"../src/h.js","original":{"line":3,"column":19}},{"generated":{"line":17,"column":21},"source":"../src/h.js","original":{"line":3,"column":4}},{"name":"chld","generated":{"line":18,"column":0},"source":"../src/h.js","original":{"line":4,"column":4}},{"generated":{"line":18,"column":11},"source":"../src/h.js","original":{"line":4,"column":11}},{"name":"concat","generated":{"line":18,"column":23},"source":"../src/h.js","original":{"line":4,"column":14}},{"generated":{"line":18,"column":29},"source":"../src/h.js","original":{"line":4,"column":11}},{"generated":{"line":18,"column":61},"source":"../src/h.js","original":{"line":4,"column":24}},{"name":"concat","generated":{"line":18,"column":74},"source":"../src/h.js","original":{"line":4,"column":27}},{"generated":{"line":18,"column":80},"source":"../src/h.js","original":{"line":4,"column":24}},{"name":"chld","generated":{"line":18,"column":113},"source":"../src/h.js","original":{"line":4,"column":37}},{"generated":{"line":18,"column":117},"source":"../src/h.js","original":{"line":4,"column":24}},{"generated":{"line":18,"column":119},"source":"../src/h.js","original":{"line":4,"column":11}},{"generated":{"line":18,"column":121},"source":"../src/h.js","original":{"line":4,"column":4}},{"generated":{"line":18,"column":122},"source":"../src/h.js","original":{"line":2,"column":47}},{"generated":{"line":18,"column":123},"source":"../src/h.js","original":{"line":4,"column":44}},{"generated":{"line":19,"column":0},"source":"../src/h.js","original":{"line":5,"column":4}},{"generated":{"line":19,"column":8},"source":"../src/h.js","original":{"line":5,"column":8}},{"generated":{"line":19,"column":9},"source":"../src/h.js","original":{"line":5,"column":9}},{"name":"type","generated":{"line":19,"column":10},"source":"../src/h.js","original":{"line":5,"column":10}},{"name":"func","generated":{"line":19,"column":15},"source":"../src/h.js","original":{"line":5,"column":15}},{"generated":{"line":19,"column":19},"source":"../src/h.js","original":{"line":5,"column":4}},{"generated":{"line":19,"column":21},"source":"../src/h.js","original":{"line":5,"column":21}},{"generated":{"line":19,"column":28},"source":"../src/h.js","original":{"line":5,"column":28}},{"name":"component","generated":{"line":20,"column":0},"source":"../src/h.js","original":{"line":6,"column":8}},{"name":"type","generated":{"line":20,"column":19},"source":"../src/h.js","original":{"line":6,"column":19}},{"generated":{"line":20,"column":23},"source":"../src/h.js","original":{"line":5,"column":28}},{"name":"vnode","generated":{"line":21,"column":0},"source":"../src/h.js","original":{"line":7,"column":8}},{"name":"type","generated":{"line":21,"column":15},"source":"../src/h.js","original":{"line":7,"column":15}},{"name":"func","generated":{"line":21,"column":20},"source":"../src/h.js","original":{"line":7,"column":20}},{"generated":{"line":21,"column":24},"source":"../src/h.js","original":{"line":7,"column":15}},{"name":"Object","generated":{"line":21,"column":25},"source":"../src/h.js","original":{"line":7,"column":25}},{"name":"assign","generated":{"line":21,"column":32},"source":"../src/h.js","original":{"line":7,"column":32}},{"generated":{"line":21,"column":38},"source":"../src/h.js","original":{"line":7,"column":25}},{"generated":{"line":21,"column":39},"source":"../src/h.js","original":{"line":7,"column":39}},{"generated":{"line":21,"column":41},"source":"../src/h.js","original":{"line":7,"column":25}},{"name":"attr","generated":{"line":21,"column":43},"source":"../src/h.js","original":{"line":7,"column":43}},{"generated":{"line":21,"column":47},"source":"../src/h.js","original":{"line":7,"column":25}},{"name":"type","generated":{"line":21,"column":49},"source":"../src/h.js","original":{"line":7,"column":49}},{"name":"state","generated":{"line":21,"column":54},"source":"../src/h.js","original":{"line":7,"column":54}},{"generated":{"line":21,"column":59},"source":"../src/h.js","original":{"line":7,"column":25}},{"generated":{"line":21,"column":60},"source":"../src/h.js","original":{"line":7,"column":15}},{"name":"chld","generated":{"line":21,"column":62},"source":"../src/h.js","original":{"line":7,"column":62}},{"generated":{"line":21,"column":66},"source":"../src/h.js","original":{"line":7,"column":15}},{"generated":{"line":21,"column":67},"source":"../src/h.js","original":{"line":5,"column":28}},{"name":"attr","generated":{"line":22,"column":0},"source":"../src/h.js","original":{"line":8,"column":8}},{"generated":{"line":22,"column":18},"source":"../src/h.js","original":{"line":5,"column":28}},{"name":"chld","generated":{"line":23,"column":0},"source":"../src/h.js","original":{"line":9,"column":8}},{"generated":{"line":24,"column":0},"source":"../src/h.js","original":{"line":5,"column":28}},{"generated":{"line":24,"column":5},"source":"../src/h.js","original":{"line":5,"column":21}},{"generated":{"line":25,"column":0},"source":"../src/h.js","original":{"line":11,"column":4}},{"generated":{"line":25,"column":8},"source":"../src/h.js","original":{"line":11,"column":8}},{"name":"type","generated":{"line":25,"column":15},"source":"../src/h.js","original":{"line":11,"column":15}},{"generated":{"line":25,"column":19},"source":"../src/h.js","original":{"line":11,"column":8}},{"generated":{"line":25,"column":24},"source":"../src/h.js","original":{"line":11,"column":24}},{"generated":{"line":25,"column":34},"source":"../src/h.js","original":{"line":11,"column":4}},{"generated":{"line":25,"column":36},"source":"../src/h.js","original":{"line":11,"column":36}},{"name":"type","generated":{"line":25,"column":43},"source":"../src/h.js","original":{"line":11,"column":43}},{"name":"attr","generated":{"line":25,"column":48},"source":"../src/h.js","original":{"line":11,"column":48}},{"generated":{"line":25,"column":52},"source":"../src/h.js","original":{"line":11,"column":43}},{"name":"chld","generated":{"line":25,"column":54},"source":"../src/h.js","original":{"line":11,"column":54}},{"generated":{"line":25,"column":58},"source":"../src/h.js","original":{"line":11,"column":43}},{"generated":{"line":25,"column":59},"source":"../src/h.js","original":{"line":11,"column":36}},{"generated":{"line":26,"column":0},"source":"../src/h.js","original":{"line":12,"column":4}},{"generated":{"line":26,"column":11},"source":"../src/h.js","original":{"line":12,"column":11}},{"name":"tag","generated":{"line":26,"column":13},"source":"../src/h.js","original":{"line":12,"column":12}},{"name":"type","generated":{"line":26,"column":18},"source":"../src/h.js","original":{"line":12,"column":17}},{"generated":{"line":26,"column":22},"source":"../src/h.js","original":{"line":12,"column":11}},{"name":"attr","generated":{"line":26,"column":24},"source":"../src/h.js","original":{"line":12,"column":23}},{"generated":{"line":26,"column":34},"source":"../src/h.js","original":{"line":12,"column":11}},{"name":"chld","generated":{"line":26,"column":36},"source":"../src/h.js","original":{"line":12,"column":29}},{"generated":{"line":26,"column":46},"source":"../src/h.js","original":{"line":12,"column":11}},{"generated":{"line":26,"column":48},"source":"../src/h.js","original":{"line":12,"column":4}},{"generated":{"line":27,"column":0},"source":"../src/h.js","original":{"line":13,"column":1}}],"sources":{"../src/h.js":"\nexport default function h(type, attr, ...chld) {\n    attr = attr || {}\n    chld = [].concat(...[].concat(...chld)) //flatten children into a single array\n    if (!!type.func) return {\n        component: type,\n        vnode: type.func(Object.assign({}, attr, type.state), chld),\n        attr,\n        chld,\n    }\n    if (typeof type === 'function') return type(attr, chld)\n    return {tag: type, attr, chld}\n}\n"},"lineCount":null}},"hash":"6a180555f86ba12db5f750da9e4b4b3a","cacheData":{"env":{}}}